<annotation>
	<folder></folder>
	<filename>IM-0549-0001-0002_jpeg.rf.f036d07b74a5e2187f7b9dadad079d4d.jpg</filename>
	<path>IM-0549-0001-0002_jpeg.rf.f036d07b74a5e2187f7b9dadad079d4d.jpg</path>
	<source>
		<database>roboflow.com</database>
	</source>
	<size>
		<width>640</width>
		<height>640</height>
		<depth>3</depth>
	</size>
	<segmented>0</segmented>
	<object>
		<name>no-pneumonia</name>
		<pose>Unspecified</pose>
		<truncated>0</truncated>
		<difficult>0</difficult>
		<occluded>0</occluded>
		<bndbox>
			<xmin>306</xmin>
			<xmax>311</xmax>
			<ymin>75</ymin>
			<ymax>84</ymax>
		</bndbox>
		<polygon>
			<x1>309.958159</x1>
			<y1>75.87822</y1>
			<x2>306.276151</x2>
			<y2>73.629977</y2>
			<x3>305.271967</x3>
			<y3>76.252927</y3>
			<x4>308.786611</x4>
			<y4>82.810304</y4>
			<x5>309.958159</x5>
			<y5>81.498829</y5>
			<x6>309.958159</x6>
			<y6>75.87822</y6>
		</polygon>
	</object>
	<object>
		<name>no-pneumonia</name>
		<pose>Unspecified</pose>
		<truncated>0</truncated>
		<difficult>0</difficult>
		<occluded>0</occluded>
		<bndbox>
			<xmin>65</xmin>
			<xmax>321</xmax>
			<ymin>76</ymin>
			<ymax>545</ymax>
		</bndbox>
		<polygon>
			<x1>67.782427</x1>
			<y1>543.700234</y1>
			<x2>70.627615</x2>
			<y2>536.018735</y2>
			<x3>73.138075</x3>
			<y3>535.081967</y3>
			<x4>81.338912</x4>
			<y4>524.40281</y4>
			<x5>93.221757</x5>
			<y5>512.224824</y5>
			<x6>108.619247</x6>
			<y6>500.234192</y6>
			<x7>123.34728</x7>
			<y7>491.241218</y7>
			<x8>142.761506</x8>
			<y8>483.372365</y8>
			<x9>145.774059</x9>
			<y9>483.372365</y9>
			<x10>145.774059</x10>
			<y10>487.119438</y10>
			<x11>151.129707</x11>
			<y11>487.868852</y11>
			<x12>153.472803</x12>
			<y12>491.241218</y12>
			<x13>155.8159</x13>
			<y13>490.491803</y13>
			<x14>158.493724</x14>
			<y14>492.36534</y14>
			<x15>157.991632</x15>
			<y15>489.180328</y15>
			<x16>161.171548</x16>
			<y16>488.24356</y16>
			<x17>162.677824</x17>
			<y17>489.180328</y17>
			<x18>162.677824</x18>
			<y18>491.803279</y18>
			<x19>164.518828</x19>
			<y19>491.990632</y19>
			<x20>169.539749</x20>
			<y20>487.119438</y20>
			<x21>172.384937</x21>
			<y21>486.18267</y21>
			<x22>169.539749</x22>
			<y22>483.372365</y22>
			<x23>160.83682</x23>
			<y23>483.372365</y23>
			<x24>153.974895</x24>
			<y24>480.936768</y24>
			<x25>172.552301</x25>
			<y25>477.377049</y25>
			<x26>215.732218</x26>
			<y26>475.87822</y26>
			<x27>231.464435</x27>
			<y27>474.004684</y27>
			<x28>241.171548</x28>
			<y28>472.131148</y28>
			<x29>244.351464</x29>
			<y29>468.571429</y29>
			<x30>244.686192</x30>
			<y30>463.325527</y30>
			<x31>238.661088</x31>
			<y31>445.714286</y31>
			<x32>235.648536</x32>
			<y32>427.35363</y32>
			<x33>235.313808</x33>
			<y33>405.995316</y33>
			<x34>238.32636</x34>
			<y34>379.765808</y34>
			<x35>241.004184</x35>
			<y35>369.274005</y35>
			<x36>247.029289</x36>
			<y36>354.660422</y36>
			<x37>256.401674</x37>
			<y37>336.674473</y37>
			<x38>265.104603</x38>
			<y38>315.316159</y38>
			<x39>270.794979</x39>
			<y39>306.323185</y39>
			<x40>271.129707</x40>
			<y40>303.325527</y40>
			<x41>269.121339</x41>
			<y41>297.704918</y41>
			<x42>271.129707</x42>
			<y42>292.459016</y42>
			<x43>271.129707</x43>
			<y43>284.590164</y43>
			<x44>273.138075</x44>
			<y44>281.592506</y44>
			<x45>273.472803</x45>
			<y45>275.971897</y45>
			<x46>276.150628</x46>
			<y46>268.103044</y46>
			<x47>278.661088</x47>
			<y47>264.543326</y47>
			<x48>281.338912</x48>
			<y48>266.791569</y48>
			<x49>286.861925</x49>
			<y49>261.733021</y49>
			<x50>286.192469</x50>
			<y50>236.252927</y50>
			<x51>287.866109</x51>
			<y51>230.632319</y51>
			<x52>292.217573</x52>
			<y52>228.009368</y52>
			<x53>298.74477</x53>
			<y53>216.955504</y53>
			<x54>301.087866</x54>
			<y54>219.203747</y54>
			<x55>301.924686</x55>
			<y55>217.892272</y55>
			<x56>301.589958</x56>
			<y56>213.770492</y56>
			<x57>297.90795</x57>
			<y57>212.271663</y57>
			<x58>293.054393</x58>
			<y58>201.217799</y58>
			<x59>288.535565</x59>
			<y59>199.531616</y59>
			<x60>283.849372</x60>
			<y60>188.665105</y60>
			<x61>283.514644</x61>
			<y61>184.918033</y61>
			<x62>286.527197</x62>
			<y62>174.800937</y62>
			<x63>288.702929</x63>
			<y63>172.740047</y63>
			<x64>296.401674</x64>
			<y64>173.114754</y64>
			<x65>302.594142</x65>
			<y65>167.306792</y65>
			<x66>304.267782</x66>
			<y66>162.435597</y66>
			<x67>301.757322</x67>
			<y67>157.002342</y67>
			<x68>295.230126</x68>
			<y68>154.566745</y68>
			<x69>297.07113</x69>
			<y69>151.381733</y69>
			<x70>308.786611</x70>
			<y70>150.632319</y70>
			<x71>313.472803</x71>
			<y71>147.259953</y71>
			<x72>316.485356</x72>
			<y72>148.758782</y72>
			<x73>317.824268</x73>
			<y73>148.009368</y73>
			<x74>318.661088</x74>
			<y74>145.948478</y74>
			<x75>314.309623</x75>
			<y75>143.325527</y75>
			<x76>318.158996</x76>
			<y76>141.639344</y76>
			<x77>320</x77>
			<y77>138.079625</y77>
			<x78>319.665272</x78>
			<y78>124.964871</y78>
			<x79>315.648536</x79>
			<y79>120.468384</y79>
			<x80>320</x80>
			<y80>115.222482</y80>
			<x81>320.334728</x81>
			<y81>112.599532</y81>
			<x82>314.811715</x82>
			<y82>110.913349</y82>
			<x83>311.464435</x83>
			<y83>113.5363</y83>
			<x84>308.786611</x84>
			<y84>110.163934</y84>
			<x85>307.112971</x85>
			<y85>110.163934</y85>
			<x86>308.786611</x86>
			<y86>106.791569</y86>
			<x87>313.138075</x87>
			<y87>105.29274</y87>
			<x88>313.640167</x88>
			<y88>103.23185</y88>
			<x89>308.786611</x89>
			<y89>99.297424</y89>
			<x90>301.422594</x90>
			<y90>99.672131</y90>
			<x91>302.259414</x91>
			<y91>91.990632</y91>
			<x92>298.74477</x92>
			<y92>88.056206</y92>
			<x93>295.230126</x93>
			<y93>87.119438</y93>
			<x94>298.912134</x94>
			<y94>84.871194</y94>
			<x95>298.74477</x95>
			<y95>77.93911</y95>
			<x96>296.401674</x96>
			<y96>78.688525</y96>
			<x97>293.389121</x97>
			<y97>83.185012</y97>
			<x98>286.359833</x98>
			<y98>79.437939</y98>
			<x99>284.016736</x99>
			<y99>80.936768</y99>
			<x100>281.338912</x100>
			<y100>80.562061</y100>
			<x101>277.991632</x101>
			<y101>76.814988</y101>
			<x102>270.292887</x102>
			<y102>77.564403</y102>
			<x103>268.619247</x103>
			<y103>75.316159</y103>
			<x104>265.774059</x104>
			<y104>77.377049</y104>
			<x105>265.606695</x105>
			<y105>82.435597</y105>
			<x106>263.933054</x106>
			<y106>84.309133</y106>
			<x107>256.23431</x107>
			<y107>78.688525</y107>
			<x108>250.878661</x108>
			<y108>78.313817</y108>
			<x109>248.535565</x109>
			<y109>75.316159</y109>
			<x110>246.192469</x110>
			<y110>75.316159</y110>
			<x111>241.171548</x111>
			<y111>79.063232</y111>
			<x112>238.828452</x112>
			<y112>76.814988</y112>
			<x113>233.472803</x113>
			<y113>78.313817</y113>
			<x114>234.309623</x114>
			<y114>84.871194</y114>
			<x115>235.983264</x115>
			<y115>87.119438</y115>
			<x116>235.146444</x116>
			<y116>88.805621</y116>
			<x117>231.129707</x117>
			<y117>88.805621</y117>
			<x118>228.451883</x118>
			<y118>85.433255</y118>
			<x119>223.430962</x119>
			<y119>88.805621</y119>
			<x120>216.066946</x120>
			<y120>89.929742</y120>
			<x121>213.389121</x121>
			<y121>93.676815</y121>
			<x122>206.359833</x122>
			<y122>95.175644</y122>
			<x123>200</x123>
			<y123>100.421546</y123>
			<x124>196.317992</x124>
			<y124>101.17096</y124>
			<x125>193.640167</x125>
			<y125>105.29274</y125>
			<x126>190.962343</x126>
			<y126>105.29274</y126>
			<x127>187.949791</x127>
			<y127>109.789227</y127>
			<x128>180.41841</x128>
			<y128>114.473068</y128>
			<x129>180.41841</x129>
			<y129>119.344262</y129>
			<x130>178.74477</x130>
			<y130>123.840749</y130>
			<x131>179.58159</x131>
			<y131>133.021077</y131>
			<x132>170.543933</x132>
			<y132>133.770492</y132>
			<x133>168.200837</x133>
			<y133>139.765808</y133>
			<x134>165.857741</x134>
			<y134>139.016393</y134>
			<x135>163.514644</x135>
			<y135>141.264637</y135>
			<x136>160.83682</x136>
			<y136>141.264637</y136>
			<x137>159.497908</x137>
			<y137>143.512881</y137>
			<x138>154.142259</x138>
			<y138>144.637002</y138>
			<x139>148.117155</x139>
			<y139>150.257611</y139>
			<x140>145.774059</x140>
			<y140>150.632319</y140>
			<x141>142.761506</x141>
			<y141>154.379391</y141>
			<x142>135.732218</x142>
			<y142>158.875878</y142>
			<x143>117.48954</x143>
			<y143>182.295082</y143>
			<x144>114.476987</x144>
			<y144>188.290398</y144>
			<x145>109.456067</x145>
			<y145>207.400468</y145>
			<x146>97.740586</x146>
			<y146>233.255269</y146>
			<x147>91.380753</x147>
			<y147>269.227166</y147>
			<x148>85.355649</x148>
			<y148>292.459016</y148>
			<x149>84.016736</x149>
			<y149>329.180328</y149>
			<x150>80.334728</x150>
			<y150>355.409836</y150>
			<x151>80</x151>
			<y151>368.149883</y151>
			<x152>81.338912</x152>
			<y152>372.64637</y152>
			<x153>74.979079</x153>
			<y153>443.091335</y153>
			<x154>70.292887</x154>
			<y154>474.566745</y154>
			<x155>70.627615</x155>
			<y155>479.437939</y155>
			<x156>67.949791</x156>
			<y156>478.313817</y156>
			<x157>65.271967</x157>
			<y157>495.550351</y157>
			<x158>63.598326</x158>
			<y158>525.526932</y158>
			<x159>64.267782</x159>
			<y159>540.515222</y159>
			<x160>65.439331</x160>
			<y160>543.325527</y160>
			<x161>67.782427</x161>
			<y161>543.700234</y161>
		</polygon>
	</object>
	<object>
		<name>no-pneumonia</name>
		<pose>Unspecified</pose>
		<truncated>0</truncated>
		<difficult>0</difficult>
		<occluded>0</occluded>
		<bndbox>
			<xmin>391</xmin>
			<xmax>583</xmax>
			<ymin>116</ymin>
			<ymax>556</ymax>
		</bndbox>
		<polygon>
			<x1>391.966527</x1>
			<y1>188.290398</y1>
			<x2>396.485356</x2>
			<y2>189.601874</y2>
			<x3>397.656904</x3>
			<y3>191.288056</y3>
			<x4>398.995816</x4>
			<y4>199.531616</y4>
			<x5>401.338912</x5>
			<y5>202.529274</y5>
			<x6>402.677824</x6>
			<y6>210.772834</y6>
			<x7>406.694561</x7>
			<y7>221.264637</y7>
			<x8>411.380753</x8>
			<y8>256.112412</y8>
			<x9>421.422594</x9>
			<y9>292.459016</y9>
			<x10>423.096234</x10>
			<y10>311.943794</y10>
			<x11>427.112971</x11>
			<y11>322.810304</y11>
			<x12>430.460251</x12>
			<y12>326.557377</y12>
			<x13>441.506276</x13>
			<y13>349.41452</y13>
			<x14>453.221757</x14>
			<y14>385.761124</y14>
			<x15>459.58159</x15>
			<y15>401.124122</y15>
			<x16>469.623431</x16>
			<y16>415.737705</y16>
			<x17>482.343096</x17>
			<y17>444.590164</y17>
			<x18>485.690377</x18>
			<y18>455.831382</y18>
			<x19>487.698745</x19>
			<y19>471.194379</y19>
			<x20>491.046025</x20>
			<y20>477.93911</y20>
			<x21>491.715481</x21>
			<y21>501.545667</y21>
			<x22>509.288703</x22>
			<y22>508.852459</y22>
			<x23>530.711297</x23>
			<y23>522.716628</y23>
			<x24>537.740586</x24>
			<y24>528.337237</y24>
			<x25>549.958159</x25>
			<y25>543.512881</y25>
			<x26>551.631799</x26>
			<y26>548.009368</y26>
			<x27>556.485356</x27>
			<y27>550.819672</y27>
			<x28>556.987448</x28>
			<y28>553.255269</y28>
			<x29>559.832636</x29>
			<y29>555.316159</y29>
			<x30>561.338912</x30>
			<y30>553.629977</y30>
			<x31>562.677824</x31>
			<y31>542.763466</y31>
			<x32>561.67364</x32>
			<y32>539.765808</y32>
			<x33>562.677824</x33>
			<y33>531.522248</y33>
			<x34>562.008368</x34>
			<y34>511.662763</y34>
			<x35>564.016736</x35>
			<y35>508.665105</y35>
			<x36>563.34728</x36>
			<y36>505.29274</y36>
			<x37>565.020921</x37>
			<y37>503.044496</y37>
			<x38>563.682008</x38>
			<y38>500.796253</y38>
			<x39>564.351464</x39>
			<y39>496.674473</y39>
			<x40>561.67364</x40>
			<y40>491.803279</y40>
			<x41>561.67364</x41>
			<y41>483.559719</y41>
			<x42>566.694561</x42>
			<y42>480.562061</y42>
			<x43>565.020921</x43>
			<y43>477.564403</y43>
			<x44>568.033473</x44>
			<y44>460.702576</y44>
			<x45>571.046025</x45>
			<y45>452.833724</y45>
			<x46>570.376569</x46>
			<y46>445.339578</y46>
			<x47>572.384937</x47>
			<y47>431.47541</y47>
			<x48>568.033473</x48>
			<y48>421.733021</y48>
			<x49>568.702929</x49>
			<y49>418.735363</y49>
			<x50>567.029289</x50>
			<y50>416.112412</y50>
			<x51>571.380753</x51>
			<y51>413.864169</y51>
			<x52>570.711297</x52>
			<y52>404.12178</y52>
			<x53>572.050209</x53>
			<y53>398.875878</y53>
			<x54>577.405858</x54>
			<y54>396.627635</y54>
			<x55>574.393305</x55>
			<y55>393.629977</y55>
			<x56>580.753138</x56>
			<y56>391.381733</y56>
			<x57>580.083682</x57>
			<y57>382.388759</y57>
			<x58>581.422594</x58>
			<y58>380.140515</y58>
			<x59>581.757322</x59>
			<y59>373.021077</y59>
			<x60>580.41841</x60>
			<y60>358.407494</y60>
			<x61>574.728033</x61>
			<y61>355.035129</y61>
			<x62>574.393305</x62>
			<y62>350.913349</y62>
			<x63>572.050209</x63>
			<y63>348.665105</y63>
			<x64>571.715481</x64>
			<y64>340.046838</y64>
			<x65>569.707113</x65>
			<y65>337.04918</y65>
			<x66>569.707113</x66>
			<y66>334.42623</y66>
			<x67>567.029289</x67>
			<y67>331.803279</y67>
			<x68>566.694561</x68>
			<y68>326.18267</y68>
			<x69>571.046025</x69>
			<y69>323.185012</y69>
			<x70>572.050209</x70>
			<y70>311.943794</y70>
			<x71>570.711297</x71>
			<y71>295.081967</y71>
			<x72>567.364017</x72>
			<y72>292.459016</y72>
			<x73>569.874477</x73>
			<y73>291.147541</y73>
			<x74>570.376569</x74>
			<y74>289.086651</y74>
			<x75>565.857741</x75>
			<y75>282.529274</y75>
			<x76>558.493724</x76>
			<y76>278.407494</y76>
			<x77>555.648536</x77>
			<y77>275.222482</y77>
			<x78>552.301255</x78>
			<y78>267.35363</y78>
			<x79>554.979079</x79>
			<y79>259.11007</y79>
			<x80>558.995816</x80>
			<y80>256.112412</y80>
			<x81>559.330544</x81>
			<y81>247.119438</y81>
			<x82>561.67364</x82>
			<y82>244.871194</y82>
			<x83>561.004184</x83>
			<y83>236.627635</y83>
			<x84>552.301255</x84>
			<y84>225.761124</y84>
			<x85>549.958159</x85>
			<y85>218.266979</y85>
			<x86>542.594142</x86>
			<y86>210.772834</y86>
			<x87>542.594142</x87>
			<y87>208.149883</y87>
			<x88>535.39749</x88>
			<y88>205.339578</y88>
			<x89>531.213389</x89>
			<y89>199.531616</y89>
			<x90>530.543933</x90>
			<y90>190.913349</y90>
			<x91>532.050209</x91>
			<y91>189.227166</y91>
			<x92>537.740586</x92>
			<y92>189.976581</y92>
			<x93>540.585774</x93>
			<y93>188.290398</y93>
			<x94>532.217573</x94>
			<y94>181.17096</y94>
			<x95>530.543933</x95>
			<y95>174.800937</y95>
			<x96>522.343096</x96>
			<y96>168.24356</y96>
			<x97>519.665272</x97>
			<y97>162.997658</y97>
			<x98>511.297071</x98>
			<y98>157.002342</y98>
			<x99>509.790795</x99>
			<y99>153.067916</y99>
			<x100>506.276151</x100>
			<y100>151.007026</y100>
			<x101>503.263598</x101>
			<y101>146.135831</y101>
			<x102>494.560669</x102>
			<y102>145.761124</y102>
			<x103>490.543933</x103>
			<y103>148.384075</y103>
			<x104>486.192469</x104>
			<y104>146.510539</y104>
			<x105>490.376569</x105>
			<y105>143.700234</y105>
			<x106>489.205021</x106>
			<y106>134.894614</y106>
			<x107>487.196653</x107>
			<y107>134.894614</y107>
			<x108>484.518828</x108>
			<y108>140.140515</y108>
			<x109>482.175732</x109>
			<y109>139.016393</y109>
			<x110>481.67364</x110>
			<y110>141.077283</y110>
			<x111>479.497908</x111>
			<y111>142.388759</y111>
			<x112>472.468619</x112>
			<y112>138.266979</y112>
			<x113>448.702929</x113>
			<y113>132.64637</y113>
			<x114>447.196653</x114>
			<y114>126.838407</y114>
			<x115>441.506276</x115>
			<y115>124.964871</y115>
			<x116>436.987448</x116>
			<y116>115.035129</y116>
			<x117>434.644351</x117>
			<y117>118.032787</y117>
			<x118>431.966527</x118>
			<y118>116.159251</y118>
			<x119>426.945607</x119>
			<y119>117.283372</y119>
			<x120>422.259414</x120>
			<y120>119.906323</y120>
			<x121>416.903766</x121>
			<y121>119.906323</y121>
			<x122>412.217573</x122>
			<y122>123.278689</y122>
			<x123>409.205021</x123>
			<y123>122.529274</y123>
			<x124>404.518828</x124>
			<y124>125.901639</y124>
			<x125>400.669456</x125>
			<y125>126.4637</y125>
			<x126>402.008368</x126>
			<y126>132.459016</y126>
			<x127>406.025105</x127>
			<y127>135.081967</y127>
			<x128>403.179916</x128>
			<y128>138.641686</y128>
			<x129>399.497908</x129>
			<y129>139.391101</y129>
			<x130>396.987448</x130>
			<y130>143.325527</y130>
			<x131>393.974895</x131>
			<y131>163.559719</y131>
			<x132>390.627615</x132>
			<y132>170.679157</y132>
			<x133>391.297071</x133>
			<y133>180.796253</y133>
			<x134>390.292887</x134>
			<y134>183.044496</y134>
			<x135>392.301255</x135>
			<y135>185.29274</y135>
			<x136>391.966527</x136>
			<y136>188.290398</y136>
		</polygon>
	</object>
</annotation>
