<annotation>
	<folder></folder>
	<filename>NORMAL2-IM-0374-0001-0002_jpeg.rf.b3f9bc15dc51cf31e5d9e256309f0637.jpg</filename>
	<path>NORMAL2-IM-0374-0001-0002_jpeg.rf.b3f9bc15dc51cf31e5d9e256309f0637.jpg</path>
	<source>
		<database>roboflow.com</database>
	</source>
	<size>
		<width>640</width>
		<height>640</height>
		<depth>3</depth>
	</size>
	<segmented>0</segmented>
	<object>
		<name>no-pneumonia</name>
		<pose>Unspecified</pose>
		<truncated>0</truncated>
		<difficult>0</difficult>
		<occluded>0</occluded>
		<bndbox>
			<xmin>376</xmin>
			<xmax>588</xmax>
			<ymin>103</ymin>
			<ymax>637</ymax>
		</bndbox>
		<polygon>
			<x1>582.585752</x1>
			<y1>582.973523</y1>
			<x2>583.007916</x2>
			<y2>575.804481</y2>
			<x3>585.118734</x3>
			<y3>573.849287</y3>
			<x4>585.118734</x4>
			<y4>566.028513</y4>
			<x5>582.163588</x5>
			<y5>567.331976</y5>
			<x6>582.163588</x6>
			<y6>557.556008</y6>
			<x7>584.907652</x7>
			<y7>557.230143</y7>
			<x8>585.963061</x8>
			<y8>554.297352</y8>
			<x9>585.118734</x9>
			<y9>548.431772</y9>
			<x10>583.430079</x10>
			<y10>547.12831</y10>
			<x11>585.540897</x11>
			<y11>541.91446</y11>
			<x12>585.118734</x12>
			<y12>520.407332</y12>
			<x13>577.941953</x13>
			<y13>488.472505</y13>
			<x14>577.941953</x14>
			<y14>458.492872</y14>
			<x15>576.253298</x15>
			<y15>444.806517</y15>
			<x16>568.654354</x16>
			<y16>414.826884</y16>
			<x17>572.875989</x17>
			<y17>406.354379</y17>
			<x18>572.875989</x18>
			<y18>383.543788</y18>
			<x19>564.854881</x19>
			<y19>356.822811</y19>
			<x20>555.145119</x20>
			<y20>337.922607</y20>
			<x21>558.100264</x21>
			<y21>327.494908</y21>
			<x22>557.6781</x22>
			<y22>312.505092</y22>
			<x23>555.145119</x23>
			<y23>298.818737</y23>
			<x24>552.612137</x24>
			<y24>290.997963</y24>
			<x25>537.836412</x25>
			<y25>271.446029</y25>
			<x26>542.480211</x26>
			<y26>266.232179</y26>
			<x27>544.168865</x27>
			<y27>255.152749</y27>
			<x28>543.746702</x28>
			<y28>244.725051</y28>
			<x29>539.94723</x29>
			<y29>232.342159</y29>
			<x30>534.248021</x30>
			<y30>220.936864</y30>
			<x31>527.07124</x31>
			<y31>213.11609</y31>
			<x32>513.773087</x32>
			<y32>205.621181</y32>
			<x33>518.83905</x33>
			<y33>194.541752</y33>
			<x34>520.105541</x34>
			<y34>186.069246</y34>
			<x35>512.295515</x35>
			<y35>166.191446</y35>
			<x36>482.744063</x36>
			<y36>149.898167</y36>
			<x37>479.366755</x37>
			<y37>153.808554</y37>
			<x38>472.612137</x38>
			<y38>154.460285</y38>
			<x39>461.21372</x39>
			<y39>151.85336</y39>
			<x40>459.736148</x40>
			<y40>141.099796</y40>
			<x41>465.646438</x41>
			<y41>131.323829</y41>
			<x42>466.068602</x42>
			<y42>124.154786</y42>
			<x43>459.525066</x43>
			<y43>117.311609</y43>
			<x44>446.860158</x44>
			<y44>110.142566</y44>
			<x45>435.461741</x45>
			<y45>108.187373</y45>
			<x46>420.263852</x46>
			<y46>101.670061</y46>
			<x47>400.844327</x47>
			<y47>101.670061</y47>
			<x48>384.379947</x48>
			<y48>107.535642</y48>
			<x49>375.725594</x49>
			<y49>120.89613</y49>
			<x50>374.881266</x50>
			<y50>135.885947</y50>
			<x51>379.525066</x51>
			<y51>143.05499</y51>
			<x52>384.591029</x52>
			<y52>167.820774</y52>
			<x53>387.124011</x53>
			<y53>171.07943</y53>
			<x54>393.034301</x54>
			<y54>195.193483</y54>
			<x55>398.944591</x55>
			<y55>205.621181</y55>
			<x56>404.432718</x56>
			<y56>225.173116</y56>
			<x57>416.042216</x57>
			<y57>245.050916</y57>
			<x58>419.630607</x58>
			<y58>247.983707</y58>
			<x59>421.741425</x59>
			<y59>259.714868</y59>
			<x60>428.073879</x60>
			<y60>265.580448</y60>
			<x61>431.873351</x61>
			<y61>281.221996</y61>
			<x62>440.316623</x62>
			<y62>294.90835</y62>
			<x63>444.960422</x63>
			<y63>322.281059</y63>
			<x64>449.604222</x64>
			<y64>332.708758</y64>
			<x65>453.403694</x65>
			<y65>351.608961</y65>
			<x66>459.313984</x66>
			<y66>362.688391</y66>
			<x67>464.802111</x67>
			<y67>386.150713</y67>
			<x68>469.868074</x68>
			<y68>418.737271</y68>
			<x69>472.401055</x69>
			<y69>450.020367</y69>
			<x70>471.978892</x70>
			<y70>492.382892</y70>
			<x71>473.245383</x71>
			<y71>497.596741</y71>
			<x72>469.868074</x72>
			<y72>523.665988</y72>
			<x73>457.62533</x73>
			<y73>527.576375</y73>
			<x74>461.635884</x74>
			<y74>531.812627</y74>
			<x75>500.474934</x75>
			<y75>539.633401</y75>
			<x76>519.894459</x76>
			<y76>548.757637</y76>
			<x77>535.092348</x77>
			<y77>559.185336</y77>
			<x78>554.934037</x78>
			<y78>579.389002</y78>
			<x79>575.408971</x79>
			<y79>607.739308</y79>
			<x80>580.897098</x80>
			<y80>620.773931</y80>
			<x81>582.163588</x81>
			<y81>635.763747</y81>
			<x82>583.430079</x82>
			<y82>635.763747</y82>
			<x83>583.430079</x83>
			<y83>631.201629</y83>
			<x84>586.807388</x84>
			<y84>627.942974</y84>
			<x85>584.274406</x85>
			<y85>587.535642</y85>
			<x86>582.585752</x86>
			<y86>582.973523</y86>
		</polygon>
	</object>
	<object>
		<name>no-pneumonia</name>
		<pose>Unspecified</pose>
		<truncated>0</truncated>
		<difficult>0</difficult>
		<occluded>0</occluded>
		<bndbox>
			<xmin>51</xmin>
			<xmax>278</xmax>
			<ymin>77</ymin>
			<ymax>638</ymax>
		</bndbox>
		<polygon>
			<x1>100.263852</x1>
			<y1>572.219959</y1>
			<x2>115.883905</x2>
			<y2>560.488798</y2>
			<x3>131.503958</x3>
			<y3>552.668024</y3>
			<x4>165.699208</x4>
			<y4>542.892057</y4>
			<x5>194.406332</x5>
			<y5>528.553971</y5>
			<x6>210.448549</x6>
			<y6>524.643585</y6>
			<x7>250.131926</x7>
			<y7>520.733198</y7>
			<x8>258.575198</x8>
			<y8>517.474542</y8>
			<x9>261.319261</x9>
			<y9>512.586558</y9>
			<x10>259.630607</x10>
			<y10>488.472505</y10>
			<x11>253.298153</x11>
			<y11>473.482688</y11>
			<x12>248.23219</x12>
			<y12>446.10998</y12>
			<x13>247.810026</x13>
			<y13>434.378819</y13>
			<x14>243.588391</x14>
			<y14>430.468432</y14>
			<x15>243.588391</x15>
			<y15>425.254582</y15>
			<x16>247.387863</x16>
			<y16>418.737271</y16>
			<x17>248.654354</x17>
			<y17>410.916497</y17>
			<x18>250.765172</x18>
			<y18>308.594705</y18>
			<x19>256.675462</x19>
			<y19>290.346232</y19>
			<x20>259.630607</x20>
			<y20>248.635438</y20>
			<x21>263.852243</x21>
			<y21>230.386965</y21>
			<x22>264.69657</x22>
			<y22>218.004073</y22>
			<x23>276.51715</x23>
			<y23>178.900204</y23>
			<x24>277.361478</x24>
			<y24>160</y24>
			<x25>276.51715</x25>
			<y25>153.482688</y25>
			<x26>271.451187</x26>
			<y26>143.706721</y26>
			<x27>270.184697</x27>
			<y27>123.503055</y27>
			<x28>260.897098</x28>
			<y28>112.423625</y28>
			<x29>259.208443</x29>
			<y29>91.568228</y29>
			<x30>254.775726</x30>
			<y30>81.466395</y30>
			<x31>243.377309</x31>
			<y31>76.252546</y31>
			<x32>223.957784</x32>
			<y32>76.904277</y32>
			<x33>213.825858</x33>
			<y33>87.331976</y33>
			<x34>211.71504</x34>
			<y34>93.197556</y34>
			<x35>197.783641</x35>
			<y35>93.849287</y35>
			<x36>191.029024</x36>
			<y36>97.107943</y36>
			<x37>188.073879</x37>
			<y37>103.625255</y37>
			<x38>173.298153</x38>
			<y38>107.535642</y38>
			<x39>168.23219</x39>
			<y39>112.749491</y39>
			<x40>162.744063</x40>
			<y40>112.09776</y40>
			<x41>158.100264</x41>
			<y41>116.008147</y41>
			<x42>150.712401</x42>
			<y42>124.806517</y42>
			<x43>147.757256</x43>
			<y43>131.97556</y43>
			<x44>147.335092</x44>
			<y44>140.448065</y44>
			<x45>145.013193</x45>
			<y45>144.032587</y45>
			<x46>131.081794</x46>
			<y46>154.460285</y46>
			<x47>122.427441</x47>
			<y47>165.86558</y47>
			<x48>117.361478</x48>
			<y48>186.069246</y48>
			<x49>118.205805</x49>
			<y49>197.800407</y49>
			<x50>106.174142</x50>
			<y50>209.205703</y50>
			<x51>94.986807</x51>
			<y51>232.342159</y51>
			<x52>92.875989</x52>
			<y52>243.421589</y52>
			<x53>94.986807</x53>
			<y53>264.928717</y53>
			<x54>84.432718</x54>
			<y54>282.525458</y54>
			<x55>78.522427</x55>
			<y55>302.729124</y55>
			<x56>77.255937</x56>
			<y56>318.370672</y56>
			<x57>78.944591</x57>
			<y57>333.360489</y57>
			<x58>70.501319</x58>
			<y58>351.608961</y58>
			<x59>65.435356</x59>
			<y59>371.160896</y59>
			<x60>65.435356</x60>
			<y60>404.399185</y60>
			<x61>57.836412</x61>
			<y61>442.199593</y61>
			<x62>57.414248</x62>
			<y62>457.841141</y62>
			<x63>59.525066</x63>
			<y63>481.303462</y63>
			<x64>52.770449</x64>
			<y64>511.934827</y64>
			<x65>51.081794</x65>
			<y65>529.531568</y65>
			<x66>51.926121</x66>
			<y66>589.490835</y66>
			<x67>49.815303</x67>
			<y67>629.898167</y67>
			<x68>50.448549</x68>
			<y68>636.089613</y68>
			<x69>63.324538</x69>
			<y69>637.06721</y69>
			<x70>65.85752</x70>
			<y70>635.112016</y70>
			<x71>73.878628</x71>
			<y71>612.301426</y71>
			<x72>94.775726</x72>
			<y72>579.389002</y72>
			<x73>100.263852</x73>
			<y73>572.219959</y73>
		</polygon>
	</object>
</annotation>
