<annotation>
	<folder></folder>
	<filename>NORMAL2-IM-0765-0001_jpeg.rf.1c606408a8446840bac011d0e561c40a.jpg</filename>
	<path>NORMAL2-IM-0765-0001_jpeg.rf.1c606408a8446840bac011d0e561c40a.jpg</path>
	<source>
		<database>roboflow.com</database>
	</source>
	<size>
		<width>640</width>
		<height>640</height>
		<depth>3</depth>
	</size>
	<segmented>0</segmented>
	<object>
		<name>no-pneumonia</name>
		<pose>Unspecified</pose>
		<truncated>0</truncated>
		<difficult>0</difficult>
		<occluded>0</occluded>
		<bndbox>
			<xmin>385</xmin>
			<xmax>586</xmax>
			<ymin>100</ymin>
			<ymax>545</ymax>
		</bndbox>
		<polygon>
			<x1>387.341772</x1>
			<y1>211.056911</y1>
			<x2>413.670886</x2>
			<y2>290.406504</y2>
			<x3>423.544304</x3>
			<y3>306.99187</y3>
			<x4>440.253165</x4>
			<y4>321.95122</y4>
			<x5>454.43038</x5>
			<y5>338.861789</y5>
			<x6>481.012658</x6>
			<y6>374.308943</y6>
			<x7>482.025316</x7>
			<y7>378.861789</y7>
			<x8>491.64557</x8>
			<y8>387.317073</y8>
			<x9>495.189873</x9>
			<y9>397.073171</y9>
			<x10>499.746835</x10>
			<y10>400.325203</y10>
			<x11>502.278481</x11>
			<y11>423.089431</y11>
			<x12>505.316456</x12>
			<y12>428.943089</y12>
			<x13>505.822785</x13>
			<y13>455.609756</y13>
			<x14>500.253165</x14>
			<y14>487.479675</y14>
			<x15>492.658228</x15>
			<y15>495.934959</y15>
			<x16>493.164557</x16>
			<y16>499.186992</y16>
			<x17>519.746835</x17>
			<y17>507.96748</y17>
			<x18>546.075949</x18>
			<y18>521.626016</y18>
			<x19>568.35443</x19>
			<y19>543.739837</y19>
			<x20>573.924051</x20>
			<y20>541.138211</y20>
			<x21>582.531646</x21>
			<y21>541.788618</y21>
			<x22>585.316456</x22>
			<y22>531.707317</y22>
			<x23>585.316456</x23>
			<y23>501.138211</y23>
			<x24>580.253165</x24>
			<y24>458.211382</y24>
			<x25>580.253165</x25>
			<y25>432.195122</y25>
			<x26>573.670886</x26>
			<y26>397.723577</y26>
			<x27>572.658228</x27>
			<y27>369.756098</y27>
			<x28>565.56962</x28>
			<y28>343.739837</y28>
			<x29>565.063291</x29>
			<y29>324.227642</y29>
			<x30>561.518987</x30>
			<y30>305.365854</y30>
			<x31>551.898734</x31>
			<y31>283.252033</y31>
			<x32>551.392405</x32>
			<y32>268.943089</y32>
			<x33>548.35443</x33>
			<y33>255.284553</y33>
			<x34>541.772152</x34>
			<y34>239.02439</y34>
			<x35>532.151899</x35>
			<y35>225.365854</y35>
			<x36>525.063291</x36>
			<y36>199.349593</y36>
			<x37>514.936709</x37>
			<y37>182.439024</y37>
			<x38>504.303797</x38>
			<y38>170.731707</y38>
			<x39>495.189873</x39>
			<y39>147.96748</y39>
			<x40>480</x40>
			<y40>127.804878</y40>
			<x41>468.101266</x41>
			<y41>115.772358</y41>
			<x42>452.405063</x42>
			<y42>106.01626</y42>
			<x43>431.139241</x43>
			<y43>98.861789</y43>
			<x44>423.037975</x44>
			<y44>100.162602</y44>
			<x45>415.949367</x45>
			<y45>107.317073</y45>
			<x46>406.835443</x46>
			<y46>109.268293</y46>
			<x47>400.253165</x47>
			<y47>115.772358</y47>
			<x48>391.898734</x48>
			<y48>131.707317</y48>
			<x49>390.379747</x49>
			<y49>138.861789</y49>
			<x50>389.367089</x50>
			<y50>158.373984</y50>
			<x51>384.303797</x51>
			<y51>175.934959</y51>
			<x52>387.341772</x52>
			<y52>193.495935</y52>
			<x53>387.341772</x53>
			<y53>211.056911</y53>
		</polygon>
	</object>
	<object>
		<name>no-pneumonia</name>
		<pose>Unspecified</pose>
		<truncated>0</truncated>
		<difficult>0</difficult>
		<occluded>0</occluded>
		<bndbox>
			<xmin>71</xmin>
			<xmax>270</xmax>
			<ymin>97</ymin>
			<ymax>584</ymax>
		</bndbox>
		<polygon>
			<x1>74.43038</x1>
			<y1>548.617886</y1>
			<x2>75.443038</x2>
			<y2>570.731707</y2>
			<x3>78.987342</x3>
			<y3>575.934959</y3>
			<x4>78.987342</x4>
			<y4>578.536585</y4>
			<x5>75.949367</x5>
			<y5>580.487805</y5>
			<x6>77.721519</x6>
			<y6>582.764228</y6>
			<x7>81.012658</x7>
			<y7>581.138211</y7>
			<x8>86.582278</x8>
			<y8>562.926829</y8>
			<x9>94.177215</x9>
			<y9>548.617886</y9>
			<x10>105.316456</x10>
			<y10>531.056911</y10>
			<x11>119.746835</x11>
			<y11>515.772358</y11>
			<x12>134.936709</x12>
			<y12>503.414634</y12>
			<x13>163.797468</x13>
			<y13>487.804878</y13>
			<x14>195.696203</x14>
			<y14>465.691057</y14>
			<x15>236.202532</x15>
			<y15>448.780488</y15>
			<x16>251.139241</x16>
			<y16>438.04878</y16>
			<x17>249.113924</x17>
			<y17>412.682927</y17>
			<x18>241.012658</x18>
			<y18>404.878049</y18>
			<x19>239.493671</x19>
			<y19>360</y19>
			<x20>235.949367</x20>
			<y20>354.796748</y20>
			<x21>235.443038</x21>
			<y21>348.943089</y21>
			<x22>230.886076</x22>
			<y22>345.04065</y22>
			<x23>230.886076</x23>
			<y23>335.934959</y23>
			<x24>221.265823</x24>
			<y24>332.682927</y24>
			<x25>222.025316</x25>
			<y25>327.154472</y25>
			<x26>229.367089</x26>
			<y26>322.926829</y26>
			<x27>221.265823</x27>
			<y27>319.674797</y27>
			<x28>222.78481</x28>
			<y28>313.170732</y28>
			<x29>230.379747</x29>
			<y29>309.268293</y29>
			<x30>232.911392</x30>
			<y30>296.910569</y30>
			<x31>240</x31>
			<y31>293.658537</y31>
			<x32>240.506329</x32>
			<y32>283.902439</y32>
			<x33>248.35443</x33>
			<y33>282.276423</y33>
			<x34>250.632911</x34>
			<y34>271.544715</y34>
			<x35>256.708861</x35>
			<y35>267.642276</y35>
			<x36>259.240506</x36>
			<y36>255.934959</y36>
			<x37>258.734177</x37>
			<y37>233.821138</y37>
			<x38>262.278481</x38>
			<y38>220.162602</y38>
			<x39>268.35443</x39>
			<y39>216.260163</y39>
			<x40>263.797468</x40>
			<y40>213.00813</y40>
			<x41>263.291139</x41>
			<y41>207.154472</y41>
			<x42>268.607595</x42>
			<y42>204.878049</y42>
			<x43>269.367089</x43>
			<y43>201.95122</y43>
			<x44>263.544304</x44>
			<y44>193.821138</y44>
			<x45>255.189873</x45>
			<y45>189.593496</y45>
			<x46>250.126582</x46>
			<y46>157.723577</y46>
			<x47>242.025316</x47>
			<y47>144.065041</y47>
			<x48>243.544304</x48>
			<y48>139.512195</y48>
			<x49>242.025316</x49>
			<y49>134.308943</y49>
			<x50>248.35443</x50>
			<y50>128.130081</y50>
			<x51>251.392405</x51>
			<y51>133.333333</y51>
			<x52>253.164557</x52>
			<y52>128.455285</y52>
			<x53>252.658228</x53>
			<y53>113.495935</y53>
			<x54>248.35443</x54>
			<y54>103.414634</y54>
			<x55>241.265823</x55>
			<y55>100.162602</y55>
			<x56>232.658228</x56>
			<y56>102.113821</y56>
			<x57>231.139241</x57>
			<y57>97.560976</y57>
			<x58>231.64557</x58>
			<y58>103.414634</y58>
			<x59>224.050633</x59>
			<y59>104.065041</y59>
			<x60>223.797468</x60>
			<y60>98.536585</y60>
			<x61>221.012658</x61>
			<y61>96.260163</y61>
			<x62>218.481013</x62>
			<y62>107.317073</y62>
			<x63>208.860759</x63>
			<y63>103.414634</y63>
			<x64>206.329114</x64>
			<y64>106.666667</y64>
			<x65>203.291139</x65>
			<y65>102.113821</y65>
			<x66>191.139241</x66>
			<y66>107.317073</y66>
			<x67>170.886076</x67>
			<y67>124.878049</y67>
			<x68>168.35443</x68>
			<y68>133.333333</y68>
			<x69>159.493671</x69>
			<y69>138.861789</y69>
			<x70>153.924051</x70>
			<y70>151.869919</y70>
			<x71>154.936709</x71>
			<y71>158.373984</y71>
			<x72>146.329114</x72>
			<y72>168.130081</y72>
			<x73>145.063291</x73>
			<y73>173.00813</y73>
			<x74>141.012658</x74>
			<y74>172.357724</y74>
			<x75>138.481013</x75>
			<y75>177.560976</y75>
			<x76>135.949367</x76>
			<y76>176.910569</y76>
			<x77>132.405063</x77>
			<y77>180.813008</y77>
			<x78>125.56962</x78>
			<y78>192.195122</y78>
			<x79>120.506329</x79>
			<y79>205.203252</y79>
			<x80>118.481013</x80>
			<y80>220.813008</y80>
			<x81>109.873418</x81>
			<y81>231.219512</y81>
			<x82>104.303797</x82>
			<y82>242.926829</y82>
			<x83>101.265823</x83>
			<y83>257.235772</y83>
			<x84>102.78481</x84>
			<y84>273.495935</y84>
			<x85>94.177215</x85>
			<y85>287.154472</y85>
			<x86>89.113924</x86>
			<y86>301.463415</y86>
			<x87>88.607595</x87>
			<y87>332.03252</y87>
			<x88>81.518987</x88>
			<y88>358.04878</y88>
			<x89>82.025316</x89>
			<y89>391.219512</y89>
			<x90>75.443038</x90>
			<y90>417.886179</y90>
			<x91>73.924051</x91>
			<y91>433.495935</y91>
			<x92>74.936709</x92>
			<y92>473.821138</y92>
			<x93>70.379747</x93>
			<y93>504.390244</y93>
			<x94>70.379747</x94>
			<y94>525.853659</y94>
			<x95>74.43038</x95>
			<y95>548.617886</y95>
		</polygon>
	</object>
</annotation>
