<annotation>
	<folder></folder>
	<filename>NORMAL2-IM-0173-0001-0001_jpeg.rf.76ca4c82e2419b4059e33075795a5ec5.jpg</filename>
	<path>NORMAL2-IM-0173-0001-0001_jpeg.rf.76ca4c82e2419b4059e33075795a5ec5.jpg</path>
	<source>
		<database>roboflow.com</database>
	</source>
	<size>
		<width>640</width>
		<height>640</height>
		<depth>3</depth>
	</size>
	<segmented>0</segmented>
	<object>
		<name>no-pneumonia</name>
		<pose>Unspecified</pose>
		<truncated>0</truncated>
		<difficult>0</difficult>
		<occluded>0</occluded>
		<bndbox>
			<xmin>388</xmin>
			<xmax>583</xmax>
			<ymin>56</ymin>
			<ymax>577</ymax>
		</bndbox>
		<polygon>
			<x1>579.141104</x1>
			<y1>513.94958</y1>
			<x2>580.122699</x2>
			<y2>501.848739</y2>
			<x3>578.650307</x3>
			<y3>499.159664</y3>
			<x4>581.104294</x4>
			<y4>478.319328</y4>
			<x5>580.613497</x5>
			<y5>450.756303</y5>
			<x6>577.668712</x6>
			<y6>436.638655</y6>
			<x7>570.306748</x7>
			<y7>418.487395</y7>
			<x8>574.723926</x8>
			<y8>383.529412</y8>
			<x9>572.269939</x9>
			<y9>368.739496</y9>
			<x10>567.852761</x10>
			<y10>353.94958</y10>
			<x11>557.055215</x11>
			<y11>334.453782</y11>
			<x12>560.490798</x12>
			<y12>315.630252</y12>
			<x13>560</x13>
			<y13>296.134454</y13>
			<x14>555.092025</x14>
			<y14>282.689076</y14>
			<x15>539.877301</x15>
			<y15>265.210084</y15>
			<x16>539.386503</x16>
			<y16>261.848739</y16>
			<x17>545.766871</x17>
			<y17>247.731092</y17>
			<x18>544.785276</x18>
			<y18>234.957983</y18>
			<x19>540.368098</x19>
			<y19>222.857143</y19>
			<x20>535.705521</x20>
			<y20>216.470588</y20>
			<x21>516.319018</x21>
			<y21>202.689076</y21>
			<x22>515.828221</x22>
			<y22>200</y22>
			<x23>522.208589</x23>
			<y23>187.226891</y23>
			<x24>520.245399</x24>
			<y24>174.453782</y24>
			<x25>505.276074</x25>
			<y25>157.310924</y25>
			<x26>490.306748</x26>
			<y26>147.563025</y26>
			<x27>489.325153</x27>
			<y27>124.033613</y27>
			<x28>479.263804</x28>
			<y28>111.596639</y28>
			<x29>471.90184</x29>
			<y29>108.907563</y29>
			<x30>469.447853</x30>
			<y30>102.857143</y30>
			<x31>455.705521</x31>
			<y31>92.773109</y31>
			<x32>454.723926</x32>
			<y32>89.411765</y32>
			<x33>446.871166</x33>
			<y33>86.05042</y33>
			<x34>445.398773</x34>
			<y34>82.689076</y34>
			<x35>431.165644</x35>
			<y35>82.016807</y35>
			<x36>427.239264</x36>
			<y36>77.310924</y36>
			<x37>424.785276</x37>
			<y37>82.689076</y37>
			<x38>421.840491</x38>
			<y38>83.361345</y38>
			<x39>419.386503</x39>
			<y39>55.12605</y39>
			<x40>418.895706</x40>
			<y40>59.159664</y40>
			<x41>412.02454</x41>
			<y41>60.504202</y41>
			<x42>410.306748</x42>
			<y42>66.890756</y42>
			<x43>406.625767</x43>
			<y43>68.571429</y43>
			<x44>405.398773</x44>
			<y44>73.613445</y44>
			<x45>401.472393</x45>
			<y45>77.647059</y45>
			<x46>400.490798</x46>
			<y46>95.798319</y46>
			<x47>387.730061</x47>
			<y47>145.546218</y47>
			<x48>386.748466</x48>
			<y48>162.352941</y48>
			<x49>391.656442</x49>
			<y49>188.571429</y49>
			<x50>396.564417</x50>
			<y50>202.016807</y50>
			<x51>406.380368</x51>
			<y51>224.201681</y51>
			<x52>428.466258</x52>
			<y52>263.865546</y52>
			<x53>440.736196</x53>
			<y53>306.218487</y53>
			<x54>448.09816</x54>
			<y54>324.369748</y54>
			<x55>452.515337</x55>
			<y55>345.210084</y55>
			<x56>476.564417</x56>
			<y56>398.991597</y56>
			<x57>480.490798</x57>
			<y57>415.12605</y57>
			<x58>482.944785</x58>
			<y58>440.672269</y58>
			<x59>480.981595</x59>
			<y59>505.882353</y59>
			<x60>482.699387</x60>
			<y60>508.907563</y60>
			<x61>499.386503</x61>
			<y61>514.285714</y61>
			<x62>515.092025</x62>
			<y62>523.02521</y62>
			<x63>535.214724</x63>
			<y63>537.142857</y63>
			<x64>548.957055</x64>
			<y64>551.260504</y64>
			<x65>565.153374</x65>
			<y65>574.789916</y65>
			<x66>573.251534</x66>
			<y66>576.470588</y66>
			<x67>579.141104</x67>
			<y67>574.453782</y67>
			<x68>579.141104</x68>
			<y68>564.369748</y68>
			<x69>581.595092</x69>
			<y69>561.008403</y69>
			<x70>579.141104</x70>
			<y70>513.94958</y70>
		</polygon>
	</object>
	<object>
		<name>no-pneumonia</name>
		<pose>Unspecified</pose>
		<truncated>0</truncated>
		<difficult>0</difficult>
		<occluded>0</occluded>
		<bndbox>
			<xmin>41</xmin>
			<xmax>271</xmax>
			<ymin>67</ymin>
			<ymax>526</ymax>
		</bndbox>
		<polygon>
			<x1>128.834356</x1>
			<y1>452.436975</y1>
			<x2>167.116564</x2>
			<y2>441.680672</y2>
			<x3>188.711656</x3>
			<y3>441.008403</y3>
			<x4>240.736196</x4>
			<y4>445.714286</y4>
			<x5>245.153374</x5>
			<y5>444.369748</y5>
			<x6>247.852761</x6>
			<y6>439.327731</y6>
			<x7>248.343558</x7>
			<y7>433.94958</y7>
			<x8>241.472393</x8>
			<y8>422.521008</y8>
			<x9>237.546012</x9>
			<y9>405.042017</y9>
			<x10>236.07362</x10>
			<y10>347.89916</y10>
			<x11>241.96319</x11>
			<y11>290.084034</y11>
			<x12>259.631902</x12>
			<y12>242.352941</y12>
			<x13>262.08589</x13>
			<y13>207.394958</y13>
			<x14>269.93865</x14>
			<y14>179.159664</y14>
			<x15>268.466258</x15>
			<y15>169.07563</y15>
			<x16>269.93865</x16>
			<y16>151.596639</y16>
			<x17>267.484663</x17>
			<y17>139.495798</y17>
			<x18>250.306748</x18>
			<y18>124.705882</y18>
			<x19>253.251534</x19>
			<y19>114.621849</y19>
			<x20>258.159509</x20>
			<y20>109.915966</y20>
			<x21>258.159509</x21>
			<y21>105.210084</y21>
			<x22>245.644172</x22>
			<y22>78.655462</y22>
			<x23>236.809816</x23>
			<y23>72.605042</y23>
			<x24>230.920245</x24>
			<y24>73.277311</y24>
			<x25>226.503067</x25>
			<y25>65.882353</y25>
			<x26>223.312883</x26>
			<y26>72.268908</y26>
			<x27>223.803681</x27>
			<y27>76.97479</y27>
			<x28>220.858896</x28>
			<y28>76.97479</y28>
			<x29>215.460123</x29>
			<y29>93.109244</y29>
			<x30>217.423313</x30>
			<y30>97.142857</y30>
			<x31>211.288344</x31>
			<y31>107.563025</y31>
			<x32>208.343558</x32>
			<y32>101.512605</y32>
			<x33>202.208589</x33>
			<y33>100.504202</y33>
			<x34>201.226994</x34>
			<y34>96.470588</y34>
			<x35>203.190184</x35>
			<y35>93.109244</y35>
			<x36>201.226994</x36>
			<y36>83.697479</y36>
			<x37>193.128834</x37>
			<y37>82.689076</y37>
			<x38>188.957055</x38>
			<y38>87.731092</y38>
			<x39>188.711656</x39>
			<y39>95.462185</y39>
			<x40>185.766871</x40>
			<y40>98.151261</y40>
			<x41>184.294479</x41>
			<y41>96.134454</y41>
			<x42>180.858896</x42>
			<y42>97.478992</y42>
			<x43>179.631902</x43>
			<y43>101.848739</y43>
			<x44>181.104294</x44>
			<y44>103.193277</y44>
			<x45>178.404908</x45>
			<y45>107.563025</y45>
			<x46>171.042945</x46>
			<y46>108.907563</y46>
			<x47>168.834356</x47>
			<y47>115.294118</y47>
			<x48>165.398773</x48>
			<y48>117.310924</y48>
			<x49>165.889571</x49>
			<y49>122.689076</y49>
			<x50>171.042945</x50>
			<y50>123.697479</y50>
			<x51>171.288344</x51>
			<y51>127.394958</y51>
			<x52>166.134969</x52>
			<y52>129.747899</y52>
			<x53>164.171779</x53>
			<y53>136.470588</y53>
			<x54>158.282209</x54>
			<y54>137.142857</y54>
			<x55>155.582822</x55>
			<y55>148.235294</y55>
			<x56>150.920245</x56>
			<y56>149.915966</y56>
			<x57>148.711656</x57>
			<y57>158.991597</y57>
			<x58>144.785276</x58>
			<y58>161.680672</y58>
			<x59>151.656442</x59>
			<y59>169.07563</y59>
			<x60>150.674847</x60>
			<y60>173.781513</y60>
			<x61>153.374233</x61>
			<y61>172.10084</y61>
			<x62>155.092025</x62>
			<y62>175.798319</y62>
			<x63>143.067485</x63>
			<y63>178.823529</y63>
			<x64>143.803681</x64>
			<y64>182.521008</y64>
			<x65>140.613497</x65>
			<y65>183.529412</y65>
			<x66>139.877301</x66>
			<y66>164.369748</y66>
			<x67>130.797546</x67>
			<y67>164.033613</y67>
			<x68>130.552147</x68>
			<y68>173.109244</y68>
			<x69>133.496933</x69>
			<y69>173.109244</y69>
			<x70>133.98773</x70>
			<y70>179.159664</y70>
			<x71>136.441718</x71>
			<y71>182.521008</y71>
			<x72>124.417178</x72>
			<y72>192.268908</y72>
			<x73>119.018405</x73>
			<y73>192.941176</y73>
			<x74>110.674847</x74>
			<y74>198.991597</y74>
			<x75>110.429448</x75>
			<y75>202.016807</y75>
			<x76>112.392638</x76>
			<y76>202.689076</y76>
			<x77>106.503067</x77>
			<y77>206.722689</y77>
			<x78>107.97546</x78>
			<y78>210.084034</y78>
			<x79>105.521472</x79>
			<y79>213.445378</y79>
			<x80>105.521472</x80>
			<y80>227.563025</y80>
			<x81>110.429448</x81>
			<y81>233.613445</y81>
			<x82>110.429448</x82>
			<y82>237.647059</y82>
			<x83>90.306748</x83>
			<y83>254.453782</y83>
			<x84>88.343558</x84>
			<y84>271.932773</y84>
			<x85>85.398773</x85>
			<y85>273.94958</y85>
			<x86>85.398773</x86>
			<y86>277.310924</y86>
			<x87>88.343558</x87>
			<y87>280.672269</y87>
			<x88>88.834356</x88>
			<y88>285.378151</y88>
			<x89>86.380368</x89>
			<y89>288.739496</y89>
			<x90>89.325153</x90>
			<y90>299.495798</y90>
			<x91>78.03681</x91>
			<y91>310.92437</y91>
			<x92>70.184049</x92>
			<y92>327.058824</y92>
			<x93>70.184049</x93>
			<y93>354.621849</y93>
			<x94>72.883436</x94>
			<y94>358.991597</y94>
			<x95>78.527607</x95>
			<y95>357.983193</y95>
			<x96>78.527607</x96>
			<y96>368.739496</y96>
			<x97>70.429448</x97>
			<y97>367.731092</y97>
			<x98>65.276074</x98>
			<y98>376.806723</y98>
			<x99>62.822086</x99>
			<y99>388.907563</y99>
			<x100>60.368098</x100>
			<y100>392.268908</y100>
			<x101>57.91411</x101>
			<y101>405.714286</y101>
			<x102>57.423313</x102>
			<y102>433.277311</y102>
			<x103>47.607362</x103>
			<y103>462.184874</y103>
			<x104>42.699387</x104>
			<y104>488.403361</y104>
			<x105>42.699387</x105>
			<y105>513.277311</y105>
			<x106>40.245399</x106>
			<y106>515.294118</y106>
			<x107>40.245399</x107>
			<y107>520.672269</y107>
			<x108>42.944785</x108>
			<y108>518.319328</y108>
			<x109>45.644172</x109>
			<y109>525.378151</y109>
			<x110>50.306748</x110>
			<y110>523.697479</y110>
			<x111>67.484663</x111>
			<y111>500.168067</y111>
			<x112>94.478528</x112>
			<y112>473.277311</y112>
			<x113>128.834356</x113>
			<y113>452.436975</y113>
		</polygon>
	</object>
</annotation>
