<annotation>
	<folder></folder>
	<filename>NORMAL2-IM-0975-0001_jpeg.rf.c24fcfc3f2cdc0160ebd4b1c0f981626.jpg</filename>
	<path>NORMAL2-IM-0975-0001_jpeg.rf.c24fcfc3f2cdc0160ebd4b1c0f981626.jpg</path>
	<source>
		<database>roboflow.com</database>
	</source>
	<size>
		<width>640</width>
		<height>640</height>
		<depth>3</depth>
	</size>
	<segmented>0</segmented>
	<object>
		<name>no-pneumonia</name>
		<pose>Unspecified</pose>
		<truncated>0</truncated>
		<difficult>0</difficult>
		<occluded>0</occluded>
		<bndbox>
			<xmin>388</xmin>
			<xmax>604</xmax>
			<ymin>109</ymin>
			<ymax>601</ymax>
		</bndbox>
		<polygon>
			<x1>401.736909</x1>
			<y1>156.644975</y1>
			<x2>399.693487</x2>
			<y2>159.421547</y2>
			<x3>400.102171</x3>
			<y3>167.288503</y3>
			<x4>390.293742</x4>
			<y4>176.080983</y4>
			<x5>387.43295</x5>
			<y5>193.203181</y5>
			<x6>400.91954</x6>
			<y6>233.463485</y6>
			<x7>421.353768</x7>
			<y7>270.484454</y7>
			<x8>431.979566</x8>
			<y8>280.202458</y8>
			<x9>443.831418</x9>
			<y9>300.563991</y9>
			<x10>449.961686</x10>
			<y10>307.505423</y10>
			<x11>453.231162</x11>
			<y11>315.372379</y11>
			<x12>499.003831</x12>
			<y12>375.994215</y12>
			<x13>510.446999</x13>
			<y13>396.81851</y13>
			<x14>512.899106</x14>
			<y14>406.999277</y14>
			<x15>519.846743</x15>
			<y15>420.88214</y15>
			<x16>526.794381</x16>
			<y16>443.094722</y16>
			<x17>528.837803</x17>
			<y17>461.142444</y17>
			<x18>525.159642</x18>
			<y18>481.503977</y18>
			<x19>521.890166</x19>
			<y19>488.908171</y19>
			<x20>521.481481</x20>
			<y20>496.312364</y20>
			<x21>518.212005</x21>
			<y21>506.030369</y21>
			<x22>514.738186</x22>
			<y22>510.426609</y22>
			<x23>510.446999</x23>
			<y23>511.583514</y23>
			<x24>512.899106</x24>
			<y24>519.913232</y24>
			<x25>529.859515</x25>
			<y25>522.921186</y25>
			<x26>532.311622</x26>
			<y26>525.697758</y26>
			<x27>550.293742</x27>
			<y27>533.101952</y27>
			<x28>559.693487</x28>
			<y28>539.580622</y28>
			<x29>575.427842</x29>
			<y29>556.934201</y29>
			<x30>576.653895</x30>
			<y30>560.636298</y30>
			<x31>585.236271</x31>
			<y31>570.354302</y31>
			<x32>587.279693</x32>
			<y32>576.37021</y32>
			<x33>590.54917</x33>
			<y33>578.221258</y33>
			<x34>592.183908</x34>
			<y34>584.699928</y34>
			<x35>595.453384</x35>
			<y35>587.939262</y35>
			<x36>600.561941</x36>
			<y36>600.202458</y36>
			<x37>603.218391</x37>
			<y37>583.774403</y37>
			<x38>602.401022</x38>
			<y38>560.173536</y38>
			<x39>601.583653</x39>
			<y39>550.918294</y39>
			<x40>599.948914</x40>
			<y40>548.604483</y40>
			<x41>600.357599</x41>
			<y41>540.274765</y41>
			<x42>598.722861</x42>
			<y42>537.960954</y42>
			<x43>598.722861</x43>
			<y43>532.407809</y43>
			<x44>596.679438</x44>
			<y44>530.093999</y44>
			<x45>596.679438</x45>
			<y45>522.689805</y45>
			<x46>599.948914</x46>
			<y46>520.375994</y46>
			<x47>600.357599</x47>
			<y47>494.924078</y47>
			<x48>601.992337</x48>
			<y48>486.59436</y48>
			<x49>600.766284</x49>
			<y49>479.190166</y49>
			<x50>602.401022</x50>
			<y50>474.099783</y50>
			<x51>599.131545</x51>
			<y51>451.887202</y51>
			<x52>591.775223</x52>
			<y52>436.616052</y52>
			<x53>592.592593</x53>
			<y53>430.137383</y53>
			<x54>597.496807</x54>
			<y54>417.642805</y54>
			<x55>597.905492</x55>
			<y55>406.536515</y55>
			<x56>595.0447</x56>
			<y56>394.041938</y56>
			<x57>578.288633</x57>
			<y57>369.515546</y57>
			<x58>578.697318</x58>
			<y58>358.409255</y58>
			<x59>587.279693</x59>
			<y59>347.302965</y59>
			<x60>587.688378</x60>
			<y60>338.047722</y60>
			<x61>581.966794</x61>
			<y61>323.702097</y61>
			<x62>563.167305</x62>
			<y62>309.819234</y62>
			<x63>557.854406</x63>
			<y63>284.367317</y63>
			<x64>560.102171</x64>
			<y64>280.896602</y64>
			<x65>564.597701</x65>
			<y65>279.508315</y65>
			<x66>566.436782</x66>
			<y66>276.963124</y66>
			<x67>562.758621</x67>
			<y67>263.08026</y67>
			<x68>559.08046</x68>
			<y68>256.138829</y68>
			<x69>554.789272</x69>
			<y69>252.205351</y69>
			<x70>540.485313</x70>
			<y70>248.040492</y70>
			<x71>532.924649</x71>
			<y71>230.686913</y71>
			<x72>530.472542</x72>
			<y72>215.878525</y72>
			<x73>538.237548</x73>
			<y73>208.474331</y73>
			<x74>537.420179</x74>
			<y74>201.995662</y74>
			<x75>532.311622</x75>
			<y75>196.211135</y75>
			<x76>506.155811</x76>
			<y76>184.17932</y76>
			<x77>489.808429</x77>
			<y77>169.833695</y77>
			<x78>483.269476</x78>
			<y78>167.982646</y78>
			<x79>481.83908</x79>
			<y79>164.974693</y79>
			<x80>489.399745</x80>
			<y80>161.041215</y80>
			<x81>492.056194</x81>
			<y81>154.331164</y81>
			<x82>491.238825</x82>
			<y82>147.852495</y82>
			<x83>487.560664</x83>
			<y83>145.075922</y83>
			<x84>487.560664</x84>
			<y84>142.299349</y84>
			<x85>481.83908</x85>
			<y85>142.299349</y85>
			<x86>480.613027</x86>
			<y86>139.522777</y86>
			<x87>481.83908</x87>
			<y87>136.746204</y87>
			<x88>472.643678</x88>
			<y88>127.722343</y88>
			<x89>470.191571</x89>
			<y89>127.259581</y89>
			<x90>469.782886</x90>
			<y90>124.94577</y90>
			<x91>464.878672</x91>
			<y91>122.169197</y91>
			<x92>460.791826</x92>
			<y92>122.63196</y92>
			<x93>462.01788</x93>
			<y93>119.392625</y93>
			<x94>452.209451</x94>
			<y94>118.467101</y94>
			<x95>451.800766</x95>
			<y95>113.839479</y95>
			<x96>444.444444</x96>
			<y96>111.062907</y96>
			<x97>442.401022</x97>
			<y97>107.823572</y97>
			<x98>440.561941</x98>
			<y98>108.517715</y98>
			<x99>441.37931</x99>
			<y99>110.831526</y99>
			<x100>439.948914</x100>
			<y100>111.988431</y100>
			<x101>431.366539</x101>
			<y101>111.525669</y101>
			<x102>429.323116</x102>
			<y102>109.67462</y102>
			<x103>424.214559</x103>
			<y103>114.07086</y103>
			<x104>423.192848</x104>
			<y104>117.078814</y104>
			<x105>419.106003</x105>
			<y105>116.15329</y105>
			<x106>413.793103</x106>
			<y106>119.392625</y106>
			<x107>409.297573</x107>
			<y107>126.334056</y107>
			<x108>399.489144</x108>
			<y108>130.961678</y108>
			<x109>400.102171</x109>
			<y109>133.506869</y109>
			<x110>397.650064</x110>
			<y110>136.283442</y110>
			<x111>397.650064</x111>
			<y111>139.522777</y111>
			<x112>393.563218</x112>
			<y112>142.299349</y112>
			<x113>394.380587</x113>
			<y113>147.389732</y113>
			<x114>399.489144</x114>
			<y114>150.860448</y114>
			<x115>398.467433</x115>
			<y115>154.331164</y115>
			<x116>401.736909</x116>
			<y116>156.644975</y116>
		</polygon>
	</object>
	<object>
		<name>no-pneumonia</name>
		<pose>Unspecified</pose>
		<truncated>0</truncated>
		<difficult>0</difficult>
		<occluded>0</occluded>
		<bndbox>
			<xmin>55</xmin>
			<xmax>291</xmax>
			<ymin>108</ymin>
			<ymax>538</ymax>
		</bndbox>
		<polygon>
			<x1>58.850575</x1>
			<y1>439.855387</y1>
			<x2>57.215837</x2>
			<y2>444.020246</y2>
			<x3>60.280971</x3>
			<y3>446.565437</y3>
			<x4>60.280971</x4>
			<y4>453.506869</y4>
			<x5>58.44189</x5>
			<y5>455.126537</y5>
			<x6>57.624521</x6>
			<y6>460.679682</y6>
			<x7>58.850575</x7>
			<y7>463.456255</y7>
			<x8>55.785441</x8>
			<y8>463.687636</y8>
			<x9>54.763729</x9>
			<y9>466.695589</y9>
			<x10>58.44189</x10>
			<y10>474.562545</y10>
			<x11>56.398467</x11>
			<y11>477.80188</y11>
			<x12>61.711367</x12>
			<y12>482.892263</y12>
			<x13>58.850575</x13>
			<y13>487.519884</y13>
			<x14>56.807152</x14>
			<y14>500.477223</y14>
			<x15>58.033206</x15>
			<y15>506.955893</y15>
			<x16>53.94636</x16>
			<y16>511.583514</y16>
			<x17>55.581098</x17>
			<y17>523.152567</y17>
			<x18>58.44189</x18>
			<y18>528.705712</y18>
			<x19>56.398467</x19>
			<y19>534.258858</y19>
			<x20>57.828863</x20>
			<y20>537.266811</y20>
			<x21>61.302682</x21>
			<y21>535.647144</y21>
			<x22>63.754789</x22>
			<y22>527.780188</y22>
			<x23>70.702427</x23>
			<y23>519.913232</y23>
			<x24>78.876117</x24>
			<y24>505.567607</y24>
			<x25>93.384419</x25>
			<y25>490.527838</y25>
			<x26>96.245211</x26>
			<y26>489.602314</y26>
			<x27>97.879949</x27>
			<y27>485.900217</y27>
			<x28>101.149425</x28>
			<y28>486.362979</y28>
			<x29>102.784163</x29>
			<y29>484.049168</y29>
			<x30>124.03576</x30>
			<y30>473.40564</y30>
			<x31>164.49553</x31>
			<y31>462.299349</y31>
			<x32>195.146871</x32>
			<y32>458.597252</y32>
			<x33>219.259259</x33>
			<y33>459.060014</y33>
			<x34>249.9106</x34>
			<y34>469.240781</y34>
			<x35>256.449553</x35>
			<y35>469.240781</y35>
			<x36>258.697318</x36>
			<y36>466.695589</y36>
			<x37>248.07152</x37>
			<y37>435.227766</y37>
			<x38>245.619413</x38>
			<y38>415.328995</y38>
			<x39>245.619413</x39>
			<y39>386.637744</y39>
			<x40>248.888889</x40>
			<y40>376.456978</y40>
			<x41>251.749681</x41>
			<y41>354.707158</y41>
			<x42>277.088123</x42>
			<y42>301.489516</y42>
			<x43>282.401022</x43>
			<y43>273.261027</y43>
			<x44>281.583653</x44>
			<y44>269.55893</y44>
			<x45>283.218391</x45>
			<y45>261.691974</y45>
			<x46>281.583653</x46>
			<y46>258.452639</y46>
			<x47>282.401022</x47>
			<y47>252.899494</y47>
			<x48>284.444444</x48>
			<y48>251.048445</y48>
			<x49>281.992337</x49>
			<y49>247.346349</y49>
			<x50>284.444444</x50>
			<y50>244.569776</y50>
			<x51>283.627075</x51>
			<y51>241.793203</y51>
			<x52>288.939974</x52>
			<y52>228.835864</y52>
			<x53>290.166028</x53>
			<y53>216.341287</y53>
			<x54>288.53129</x54>
			<y54>199.219089</y54>
			<x55>286.487867</x55>
			<y55>196.905278</y55>
			<x56>285.670498</x56>
			<y56>182.096891</y56>
			<x57>270.54917</x57>
			<y57>174.229935</y57>
			<x58>270.54917</x58>
			<y58>159.884309</y58>
			<x59>278.927203</x59>
			<y59>159.652928</y59>
			<x60>281.583653</x60>
			<y60>156.644975</y60>
			<x61>278.927203</x61>
			<y61>151.785973</y61>
			<x62>270.140485</x62>
			<y62>151.091829</y62>
			<x63>270.54917</x63>
			<y63>136.746204</y63>
			<x64>278.722861</x64>
			<y64>133.969631</y64>
			<x65>271.366539</x65>
			<y65>127.953724</y65>
			<x66>273.614304</x66>
			<y66>121.706435</y66>
			<x67>277.088123</x67>
			<y67>122.400578</y67>
			<x68>275.249042</x68>
			<y68>118.004338</y68>
			<x69>270.344828</x69>
			<y69>115.227766</y69>
			<x70>268.710089</x70>
			<y70>123.094722</y70>
			<x71>261.353768</x71>
			<y71>118.004338</y71>
			<x72>260.332056</x72>
			<y72>122.863341</y72>
			<x73>265.236271</x73>
			<y73>128.416486</y73>
			<x74>258.492976</x74>
			<y74>130.036153</y74>
			<x75>246.641124</x75>
			<y75>123.557484</y75>
			<x76>243.780332</x76>
			<y76>118.467101</y76>
			<x77>238.467433</x77>
			<y77>118.004338</y77>
			<x78>233.971903</x78>
			<y78>111.988431</y78>
			<x79>227.024266</x79>
			<y79>107.36081</y79>
			<x80>218.44189</x80>
			<y80>107.36081</y80>
			<x81>203.320562</x81>
			<y81>113.839479</y81>
			<x82>184.521073</x82>
			<y82>124.94577</y82>
			<x83>178.390805</x83>
			<y83>130.498915</y83>
			<x84>175.938697</x84>
			<y84>130.498915</y84>
			<x85>174.303959</x85>
			<y85>134.201012</y85>
			<x86>167.560664</x86>
			<y86>136.746204</y86>
			<x87>169.195402</x87>
			<y87>139.522777</y87>
			<x88>168.378033</x88>
			<y88>143.224873</y88>
			<x89>165.517241</x89>
			<y89>142.762111</y89>
			<x90>163.882503</x90>
			<y90>148.778019</y90>
			<x91>164.699872</x91>
			<y91>153.40564</y91>
			<x92>169.399745</x92>
			<y92>155.025307</y92>
			<x93>170.421456</x93>
			<y93>158.958785</y93>
			<x94>163.269476</x94>
			<y94>164.28055</y94>
			<x95>153.869732</x95>
			<y95>175.38684</y95>
			<x96>146.922095</x96>
			<y96>180.477223</y96>
			<x97>130.983397</x97>
			<y97>184.17932</y97>
			<x98>120.153257</x98>
			<y98>193.665944</y98>
			<x99>119.744572</x99>
			<y99>199.681851</y99>
			<x100>121.174968</x100>
			<y100>201.301518</y100>
			<x101>127.305236</x101>
			<y101>203.615329</y101>
			<x102>143.243934</x102>
			<y102>204.540853</y102>
			<x103>145.491699</x103>
			<y103>212.63919</y103>
			<x104>140.791826</x104>
			<y104>216.109906</y104>
			<x105>138.339719</x105>
			<y105>214.72162</y105>
			<x106>133.231162</x106>
			<y106>216.341287</y106>
			<x107>137.726692</x107>
			<y107>221.894432</y107>
			<x108>134.048531</x108>
			<y108>227.447578</y108>
			<x109>134.252874</x109>
			<y109>230.455531</y109>
			<x110>130.166028</x110>
			<y110>231.381056</y110>
			<x111>128.735632</x111>
			<y111>230.22415</y111>
			<x112>129.144317</x112>
			<y112>226.984816</y112>
			<x113>126.896552</x113>
			<y113>226.290672</y113>
			<x114>123.218391</x114>
			<y114>227.216197</y114>
			<x115>121.174968</x115>
			<y115>230.918294</y115>
			<x116>118.314176</x116>
			<y116>229.067245</y116>
			<x117>113.409962</x117>
			<y117>235.545915</y117>
			<x118>105.644955</x118>
			<y118>235.545915</y118>
			<x119>101.55811</x119>
			<y119>237.396963</y119>
			<x120>94.814815</x120>
			<y120>244.569776</y120>
			<x121>90.319285</x121>
			<y121>254.28778</y121>
			<x122>89.9106</x122>
			<y122>258.915401</y122>
			<x123>91.749681</x123>
			<y123>261.923355</y123>
			<x124>100.332056</x124>
			<y124>264.699928</y124>
			<x125>119.131545</x125>
			<y125>267.013738</y125>
			<x126>120.766284</x126>
			<y126>269.790311</y126>
			<x127>124.03576</x127>
			<y127>269.327549</y127>
			<x128>126.283525</x128>
			<y128>273.723789</y128>
			<x129>124.03576</x129>
			<y129>276.731743</y129>
			<x130>118.314176</x130>
			<y130>276.731743</y130>
			<x131>114.636015</x131>
			<y131>281.822126</y131>
			<x132>99.106003</x132>
			<y132>284.135936</y132>
			<x133>98.697318</x133>
			<y133>287.375271</y133>
			<x134>80.306513</x134>
			<y134>295.242227</y134>
			<x135>75.606641</x135>
			<y135>301.952278</y135>
			<x136>72.745849</x136>
			<y136>307.968185</y136>
			<x137>71.519796</x137>
			<y137>318.611714</y137>
			<x138>75.810983</x138>
			<y138>324.859002</y138>
			<x139>83.371648</x139>
			<y139>330.643529</y139>
			<x140>83.780332</x140>
			<y140>332.957339</y140>
			<x141>81.532567</x141>
			<y141>337.816341</y141>
			<x142>69.476373</x142>
			<y142>347.302965</y142>
			<x143>60.076628</x143>
			<y143>364.425163</y143>
			<x144>59.259259</x144>
			<y144>381.084599</y144>
			<x145>64.572158</x145>
			<y145>396.355748</y145>
			<x146>62.93742</x146>
			<y146>401.908894</y146>
			<x147>60.076628</x147>
			<y147>404.222704</y147>
			<x148>59.259259</x148>
			<y148>412.552422</y148>
			<x149>56.398467</x149>
			<y149>415.328995</y149>
			<x150>55.172414</x150>
			<y150>420.419378</y150>
			<x151>56.398467</x151>
			<y151>423.195951</y151>
			<x152>55.172414</x152>
			<y152>429.67462</y152>
			<x153>58.44189</x153>
			<y153>435.227766</y153>
			<x154>58.850575</x154>
			<y154>439.855387</y154>
		</polygon>
	</object>
</annotation>
